fsai_nats_app/__init__.py
fsai_nats_app/fsai_nats_app.py
fsai_nats_app-0.0.3.dist-info/LICENSE
fsai_nats_app-0.0.3.dist-info/METADATA
fsai_nats_app-0.0.3.dist-info/WHEEL
fsai_nats_app-0.0.3.dist-info/RECORD
