Metadata-Version: 2.3
Name: fsai-nats-app
Version: 0.0.3
Summary: NATS JetStream wrapper providing a FastStream-like interface for easy message handling.
License: MIT
Author: Michael Mohamed
Author-email: michael@foundationstack.com
Requires-Python: >=3.9,<3.13
Classifier: License :: OSI Approved :: MIT License
Classifier: Programming Language :: Python :: 3
Classifier: Programming Language :: Python :: 3.9
Classifier: Programming Language :: Python :: 3.10
Classifier: Programming Language :: Python :: 3.11
Classifier: Programming Language :: Python :: 3.12
Requires-Dist: loguru (>=0.6.0,<0.7.0)
Requires-Dist: nats-py (>=2.11.0,<3.0.0)
Project-URL: Homepage, https://github.com/fsai-dev/fsai-nats-app
Project-URL: Repository, https://github.com/fsai-dev/fsai-nats-app
